Workbook

Sheet Расчет ТБУ
B2: АНАЛИЗ ТОЧКИ БЕЗУБЫТОЧНОСТИ (BREAK-EVEN ANALYSIS)
B3: Кадровое агентство «track» • Расчеты на месяц (начиная с 4-го месяца)
B5: 1. Ежемесячные постоянные расходы агентства (Фикс)
B6: Статья постоянных расходов | C6: Сумма в месяц (₽) | D6: Обоснование
B7: ФОТ базовый (фикс на 6 человек команды) | C7: 630000 | D7: Обеспечение базовой жизнедеятельности команды основателей
B8: Подписки на базы резюме (hh.ru, Хабр, GetMatch) | C8: 60000 | D8: Усредненная стоимость ежемесячного продления доступов
B9: Лицензии CRM/ATS Хантфлоу | C9: 12500 | D9: 6 пользователей (37 500 ₽ за 3 месяца согласно тарифу)
B10: Маркетинг, реклама и лидогенерация | C10: 85000 | D10: Ежемесячный бюджет на поддержание входящего потока клиентов
B11: Административные расходы и инфраструктура | C11: 25500 | D11: Корпоративная связь, сервисы Яндекс 360, банковское РКО
B12: ИТОГО ПОСТОЯННЫХ РАСХОДОВ (месяц) | C12: =SUM(C7:C11) -> 813000
B15: 2. Маржинальный доход по направлениям (из Юнит-экономики)
B16: Направление подбора (Senior) | C16: Гонорар (Выручка) | D16: Переменные расходы | E16: Маржа со сделки
B17: Информационная безопасность | C17: 840000 | D17: 298000 | E17: =C17-D17 -> 542000
B18: Базы данных (DBA PostgreSQL) | C18: 768000 | D18: 287200 | E18: =C18-D18 -> 480800
B19: Разработчики 1С | C19: 720000 | D19: 280000 | E19: =C19-D19 -> 440000
B20: ML/AI инженеры | C20: 960000 | D20: 324000 | E20: =C20-D20 -> 636000
B21: DevOps/SRE | C21: 888000 | D21: 305200 | E21: =C21-D21 -> 582800
B22: СРЕДНЕЕ ЗНАЧЕНИЕ ПО АГЕНТСТВУ | C22: =AVERAGE(C17:C21) -> 835200 | D22: =AVERAGE(D17:D21) -> 298880 | E22: =AVERAGE(E17:E21) -> 536320
B25: 3. Итоговый расчет точки безубыточности (ТБУ)
B27: Постоянные расходы в месяц (Пост. Расходы): | C27: =C12 -> 813000
B28: Средняя маржинальная прибыль со сделки (Маржа): | C28: =E22 -> 536320
B30: ТОЧКА БЕЗУБЫТОЧНОСТИ (сделок в месяц): | C30: =C27/C28 -> 1.515886
B32: Примечание для защиты: Для флагманской ниши (ИБ) с маржой 542 000 ₽ точка безубыточности составляет ровно 1.50 сделок.

Sheet График ТБУ
B2: Модель зависимости финансового результата от объема продаж
B4: Кол-во сделок | C4: Постоянные расходы | D4: Полные расходы (Пост + Перем) | E4: Совокупная Выручка | F4: Чистая Прибыль
B5: 0 | C5: ='Расчет ТБУ'!$C$12 -> 813000 | D5: =C5+(B5*'Расчет ТБУ'!$D$22) -> 813000 | E5: =B5*'Расчет ТБУ'!$C$22 -> 0 | F5: =E5-D5 -> -813000
B6: 0.5 | C6: ='Расчет ТБУ'!$C$12 -> 813000 | D6: =C6+(B6*'Расчет ТБУ'!$D$22) -> 962440 | E6: =B6*'Расчет ТБУ'!$C$22 -> 417600 | F6: =E6-D6 -> -544840
B7: 1 | C7: ='Расчет ТБУ'!$C$12 -> 813000 | D7: =C7+(B7*'Расчет ТБУ'!$D$22) -> 1111880 | E7: =B7*'Расчет ТБУ'!$C$22 -> 835200 | F7: =E7-D7 -> -276680
B8: 1.5 | C8: ='Расчет ТБУ'!$C$12 -> 813000 | D8: =C8+(B8*'Расчет ТБУ'!$D$22) -> 1261320 | E8: =B8*'Расчет ТБУ'!$C$22 -> 1252800 | F8: =E8-D8 -> -8520
B9: 2 | C9: ='Расчет ТБУ'!$C$12 -> 813000 | D9: =C9+(B9*'Расчет ТБУ'!$D$22) -> 1410760 | E9: =B9*'Расчет ТБУ'!$C$22 -> 1670400 | F9: =E9-D9 -> 259640
B10: 2.5 | C10: ='Расчет ТБУ'!$C$12 -> 813000 | D10: =C10+(B10*'Расчет ТБУ'!$D$22) -> 1560200 | E10: =B10*'Расчет ТБУ'!$C$22 -> 2088000 | F10: =E10-D10 -> 527800
B11: 3 | C11: ='Расчет ТБУ'!$C$12 -> 813000 | D11: =C11+(B11*'Расчет ТБУ'!$D$22) -> 1709640 | E11: =B11*'Расчет ТБУ'!$C$22 -> 2505600 | F11: =E11-D11 -> 795960
B12: 3.5 | C12: ='Расчет ТБУ'!$C$12 -> 813000 | D12: =C12+(B12*'Расчет ТБУ'!$D$22) -> 1859080 | E12: =B12*'Расчет ТБУ'!$C$22 -> 2923200 | F12: =E12-D12 -> 1064120
B13: 4 | C13: ='Расчет ТБУ'!$C$12 -> 813000 | D13: =C13+(B13*'Расчет ТБУ'!$D$22) -> 2008520 | E13: =B13*'Расчет ТБУ'!$C$22 -> 3340800 | F13: =E13-D13 -> 1332280
