Workbook

Sheet Дашборд
B2: ПРОЕКТ: IT-КАДРОВОЕ АГЕНТСТВО «track»
B3: Сводный дашборд финансовых сценариев (12 месяцев)
B5: Сводная таблица по итогам 12 месяцев
B6: Сценарий | C6: Всего закрытий | D6: Совокупная Выручка | E6: Совокупные Расходы | F6: Чистая Прибыль за год | G6: Финальный кэш (М12)
B7: Пессимистичный | C7: ='Пессимистичный сценарий'!B16 -> 18 | D7: ='Пессимистичный сценарий'!C16 -> 11050000 | E7: ='Пессимистичный сценарий'!D16 -> 8050000 | F7: ='Пессимистичный сценарий'!E16 -> 3000000 | G7: ='Пессимистичный сценарий'!F15 -> 3000000
B8: Базовый | C8: ='Базовый сценарий'!B16 -> 38.5 | D8: ='Базовый сценарий'!C16 -> 24750000 | E8: ='Базовый сценарий'!D16 -> 11900000 | F8: ='Базовый сценарий'!E16 -> 12850000 | G8: ='Базовый сценарий'!F15 -> 12850000
B9: Оптимистичный | C9: ='Оптимистичный сценарий'!B16 -> 59.5 | D9: ='Оптимистичный сценарий'!C16 -> 38700000 | E9: ='Оптимистичный сценарий'!D16 -> 20700000 | F9: ='Оптимистичный сценарий'!E16 -> 18000000 | G9: ='Оптимистичный сценарий'!F15 -> 18000000
B12: Данные для графиков
B14: Месяц | C14: Выручка: Пессим. | D14: Выручка: Базовый | E14: Выручка: Оптим. | G14: Прибыль: Пессим. | H14: Прибыль: Базовый | I14: Прибыль: Оптим. | K14: Кэш: Пессим. | L14: Кэш: Базовый | M14: Кэш: Оптим.
B15: М1 | C15: ='Пессимистичный сценарий'!C4 -> 0 | D15: ='Базовый сценарий'!C4 -> 0 | E15: ='Оптимистичный сценарий'!C4 -> 0 | G15: ='Пессимистичный сценарий'!E4 -> -800000 | H15: ='Базовый сценарий'!E4 -> -800000 | I15: ='Оптимистичный сценарий'!E4 -> -800000 | K15: ='Пессимистичный сценарий'!F4 -> -800000 | L15: ='Базовый сценарий'!F4 -> -800000 | M15: ='Оптимистичный сценарий'!F4 -> -800000
B16: М2 | C16: ='Пессимистичный сценарий'!C5 -> 0 | D16: ='Базовый сценарий'!C5 -> 600000 | E16: ='Оптимистичный сценарий'!C5 -> 1200000 | G16: ='Пессимистичный сценарий'!E5 -> -200000 | H16: ='Базовый сценарий'!E5 -> 300000 | I16: ='Оптимистичный сценарий'!E5 -> 800000 | K16: ='Пессимистичный сценарий'!F5 -> -1000000 | L16: ='Базовый сценарий'!F5 -> -500000 | M16: ='Оптимистичный сценарий'!F5 -> 0
B17: М3 | C17: ='Пессимистичный сценарий'!C6 -> 300000 | D17: ='Базовый сценарий'!C6 -> 1200000 | E17: ='Оптимистичный сценарий'!C6 -> 2400000 | G17: ='Пессимистичный сценарий'!E6 -> 200000 | H17: ='Базовый сценарий'!E6 -> 600000 | I17: ='Оптимистичный сценарий'!E6 -> 2000000 | K17: ='Пессимистичный сценарий'!F6 -> -800000 | L17: ='Базовый сценарий'!F6 -> 100000 | M17: ='Оптимистичный сценарий'!F6 -> 2000000
B18: М4 | C18: ='Пессимистичный сценарий'!C7 -> 400000 | D18: ='Базовый сценарий'!C7 -> 1400000 | E18: ='Оптимистичный сценарий'!C7 -> 2500000 | G18: ='Пессимистичный сценарий'!E7 -> 250000 | H18: ='Базовый сценарий'!E7 -> 750000 | I18: ='Оптимистичный сценарий'!E7 -> 1000000 | K18: ='Пессимистичный сценарий'!F7 -> -550000 | L18: ='Базовый сценарий'!F7 -> 850000 | M18: ='Оптимистичный сценарий'!F7 -> 3000000
B19: М5 | C19: ='Пессимистичный сценарий'!C8 -> 600000 | D19: ='Базовый сценарий'!C8 -> 1650000 | E19: ='Оптимистичный сценарий'!C8 -> 2700000 | G19: ='Пессимистичный сценарий'!E8 -> 250000 | H19: ='Базовый сценарий'!E8 -> 1100000 | I19: ='Оптимистичный сценарий'!E8 -> 1000000 | K19: ='Пессимистичный сценарий'!F8 -> -300000 | L19: ='Базовый сценарий'!F8 -> 1950000 | M19: ='Оптимистичный сценарий'!F8 -> 4000000
B20: М6 | C20: ='Пессимистичный сценарий'!C9 -> 950000 | D20: ='Базовый сценарий'!C9 -> 1900000 | E20: ='Оптимистичный сценарий'!C9 -> 2850000 | G20: ='Пессимистичный сценарий'!E9 -> 150000 | H20: ='Базовый сценарий'!E9 -> 900000 | I20: ='Оптимистичный сценарий'!E9 -> 1000000 | K20: ='Пессимистичный сценарий'!F9 -> -150000 | L20: ='Базовый сценарий'!F9 -> 2850000 | M20: ='Оптимистичный сценарий'!F9 -> 5000000
B21: М7 | C21: ='Пессимистичный сценарий'!C10 -> 1000000 | D21: ='Базовый сценарий'!C10 -> 2200000 | E21: ='Оптимистичный сценарий'!C10 -> 3200000 | G21: ='Пессимистичный сценарий'!E10 -> 450000 | H21: ='Базовый сценарий'!E10 -> 1300000 | I21: ='Оптимистичный сценарий'!E10 -> 1500000 | K21: ='Пессимистичный сценарий'!F10 -> 300000 | L21: ='Базовый сценарий'!F10 -> 4150000 | M21: ='Оптимистичный сценарий'!F10 -> 6500000
B22: М8 | C22: ='Пессимистичный сценарий'!C11 -> 1200000 | D22: ='Базовый сценарий'!C11 -> 2500000 | E22: ='Оптимистичный сценарий'!C11 -> 3600000 | G22: ='Пессимистичный сценарий'!E11 -> 600000 | H22: ='Базовый сценарий'!E11 -> 1500000 | I22: ='Оптимистичный сценарий'!E11 -> 2000000 | K22: ='Пессимистичный сценарий'!F11 -> 900000 | L22: ='Базовый сценарий'!F11 -> 5650000 | M22: ='Оптимистичный сценарий'!F11 -> 8500000
B23: М9 | C23: ='Пессимистичный сценарий'!C12 -> 1350000 | D23: ='Базовый сценарий'!C12 -> 2700000 | E23: ='Оптимистичный сценарий'!C12 -> 4050000 | G23: ='Пессимистичный сценарий'!E12 -> 600000 | H23: ='Базовый сценарий'!E12 -> 1400000 | I23: ='Оптимистичный сценарий'!E12 -> 2000000 | K23: ='Пессимистичный сценарий'!F12 -> 1500000 | L23: ='Базовый сценарий'!F12 -> 7050000 | M23: ='Оптимистичный сценарий'!F12 -> 10500000
B24: М10 | C24: ='Пессимистичный сценарий'!C13 -> 1500000 | D24: ='Базовый сценарий'!C13 -> 3100000 | E24: ='Оптимистичный сценарий'!C13 -> 4800000 | G24: ='Пессимистичный сценарий'!E13 -> 500000 | H24: ='Базовый сценарий'!E13 -> 1800000 | I24: ='Оптимистичный сценарий'!E13 -> 2500000 | K24: ='Пессимистичный сценарий'!F13 -> 2000000 | L24: ='Базовый сценарий'!F13 -> 8850000 | M24: ='Оптимистичный сценарий'!F13 -> 13000000
B25: М11 | C25: ='Пессимистичный сценарий'!C14 -> 1750000 | D25: ='Базовый сценарий'!C14 -> 3500000 | E25: ='Оптимистичный сценарий'!C14 -> 5400000 | G25: ='Пессимистичный сценарий'!E14 -> 500000 | H25: ='Базовый сценарий'!E14 -> 2000000 | I25: ='Оптимистичный сценарий'!E14 -> 2500000 | K25: ='Пессимистичный сценарий'!F14 -> 2500000 | L25: ='Базовый сценарий'!F14 -> 10850000 | M25: ='Оптимистичный сценарий'!F14 -> 15500000
B26: М12 | C26: ='Пессимистичный сценарий'!C15 -> 2000000 | D26: ='Базовый сценарий'!C15 -> 4000000 | E26: ='Оптимистичный сценарий'!C15 -> 6000000 | G26: ='Пессимистичный сценарий'!E15 -> 500000 | H26: ='Базовый сценарий'!E15 -> 2000000 | I26: ='Оптимистичный сценарий'!E15 -> 2500000 | K26: ='Пессимистичный сценарий'!F15 -> 3000000 | L26: ='Базовый сценарий'!F15 -> 12850000 | M26: ='Оптимистичный сценарий'!F15 -> 18000000

Sheet Базовый сценарий
A1: Финансовая модель: Базовый сценарий
A3: Месяц | B3: Количество закрытий | C3: Выручка | D3: Расходы | E3: Чистая прибыль | F3: Накопленная прибыль
A4: Месяц 1 | B4: 0 | C4: 0 | D4: 800000 | E4: =C4-D4 -> -800000 | F4: =E4 -> -800000
A5: Месяц 2 | B5: 1 | C5: 600000 | D5: 300000 | E5: =C5-D5 -> 300000 | F5: =F4+E5 -> -500000
A6: Месяц 3 | B6: 2 | C6: 1200000 | D6: 600000 | E6: =C6-D6 -> 600000 | F6: =F5+E6 -> 100000
A7: Месяц 4 | B7: 2 | C7: 1400000 | D7: 650000 | E7: =C7-D7 -> 750000 | F7: =F6+E7 -> 850000
A8: Месяц 5 | B8: 2.5 | C8: 1650000 | D8: 550000 | E8: =C8-D8 -> 1100000 | F8: =F7+E8 -> 1950000
A9: Месяц 6 | B9: 3 | C9: 1900000 | D9: 1000000 | E9: =C9-D9 -> 900000 | F9: =F8+E9 -> 2850000
A10: Месяц 7 | B10: 3.5 | C10: 2200000 | D10: 900000 | E10: =C10-D10 -> 1300000 | F10: =F9+E10 -> 4150000
A11: Месяц 8 | B11: 4 | C11: 2500000 | D11: 1000000 | E11: =C11-D11 -> 1500000 | F11: =F10+E11 -> 5650000
A12: Месяц 9 | B12: 4 | C12: 2700000 | D12: 1300000 | E12: =C12-D12 -> 1400000 | F12: =F11+E12 -> 7050000
A13: Месяц 10 | B13: 5 | C13: 3100000 | D13: 1300000 | E13: =C13-D13 -> 1800000 | F13: =F12+E13 -> 8850000
A14: Месяц 11 | B14: 5.5 | C14: 3500000 | D14: 1500000 | E14: =C14-D14 -> 2000000 | F14: =F13+E14 -> 10850000
A15: Месяц 12 | B15: 6 | C15: 4000000 | D15: 2000000 | E15: =C15-D15 -> 2000000 | F15: =F14+E15 -> 12850000
A16: Итого / Баланс | B16: =SUM(B4:B15) -> 38.5 | C16: =SUM(C4:C15) -> 24750000 | D16: =SUM(D4:D15) -> 11900000 | E16: =SUM(E4:E15) -> 12850000 | F16: =F15 -> 12850000

Sheet Пессимистичный сценарий
A1: Финансовая модель: Пессимистичный сценарий
A3: Месяц | B3: Количество закрытий | C3: Выручка | D3: Расходы | E3: Чистая прибыль | F3: Накопленная прибыль
A4: Месяц 1 | B4: 0 | C4: 0 | D4: 800000 | E4: =C4-D4 -> -800000 | F4: =E4 -> -800000
A5: Месяц 2 | B5: 0 | C5: 0 | D5: 200000 | E5: =C5-D5 -> -200000 | F5: =F4+E5 -> -1000000
A6: Месяц 3 | B6: 1 | C6: 300000 | D6: 100000 | E6: =C6-D6 -> 200000 | F6: =F5+E6 -> -800000
A7: Месяц 4 | B7: 1 | C7: 400000 | D7: 150000 | E7: =C7-D7 -> 250000 | F7: =F6+E7 -> -550000
A8: Месяц 5 | B8: 1.2 | C8: 600000 | D8: 350000 | E8: =C8-D8 -> 250000 | F8: =F7+E8 -> -300000
A9: Месяц 6 | B9: 1.5 | C9: 950000 | D9: 800000 | E9: =C9-D9 -> 150000 | F9: =F8+E9 -> -150000
A10: Месяц 7 | B10: 1.5 | C10: 1000000 | D10: 550000 | E10: =C10-D10 -> 450000 | F10: =F9+E10 -> 300000
A11: Месяц 8 | B11: 1.8 | C11: 1200000 | D11: 600000 | E11: =C11-D11 -> 600000 | F11: =F10+E11 -> 900000
A12: Месяц 9 | B12: 2 | C12: 1350000 | D12: 750000 | E12: =C12-D12 -> 600000 | F12: =F11+E12 -> 1500000
A13: Месяц 10 | B13: 2.5 | C13: 1500000 | D13: 1000000 | E13: =C13-D13 -> 500000 | F13: =F12+E13 -> 2000000
A14: Месяц 11 | B14: 2.5 | C14: 1750000 | D14: 1250000 | E14: =C14-D14 -> 500000 | F14: =F13+E14 -> 2500000
A15: Месяц 12 | B15: 3 | C15: 2000000 | D15: 1500000 | E15: =C15-D15 -> 500000 | F15: =F14+E15 -> 3000000
A16: Итого / Баланс | B16: =SUM(B4:B15) -> 18 | C16: =SUM(C4:C15) -> 11050000 | D16: =SUM(D4:D15) -> 8050000 | E16: =SUM(E4:E15) -> 3000000 | F16: =F15 -> 3000000

Sheet Оптимистичный сценарий
A1: Финансовая модель: Оптимистичный сценарий
A3: Месяц | B3: Количество закрытий | C3: Выручка | D3: Расходы | E3: Чистая прибыль | F3: Накопленная прибыль
A4: Месяц 1 | B4: 0 | C4: 0 | D4: 800000 | E4: =C4-D4 -> -800000 | F4: =E4 -> -800000
A5: Месяц 2 | B5: 2 | C5: 1200000 | D5: 400000 | E5: =C5-D5 -> 800000 | F5: =F4+E5 -> 0
A6: Месяц 3 | B6: 4 | C6: 2400000 | D6: 400000 | E6: =C6-D6 -> 2000000 | F6: =F5+E6 -> 2000000
A7: Месяц 4 | B7: 4.2 | C7: 2500000 | D7: 1500000 | E7: =C7-D7 -> 1000000 | F7: =F6+E7 -> 3000000
A8: Месяц 5 | B8: 4.5 | C8: 2700000 | D8: 1700000 | E8: =C8-D8 -> 1000000 | F8: =F7+E8 -> 4000000
A9: Месяц 6 | B9: 5 | C9: 2850000 | D9: 1850000 | E9: =C9-D9 -> 1000000 | F9: =F8+E9 -> 5000000
A10: Месяц 7 | B10: 5.5 | C10: 3200000 | D10: 1700000 | E10: =C10-D10 -> 1500000 | F10: =F9+E10 -> 6500000
A11: Месяц 8 | B11: 5.8 | C11: 3600000 | D11: 1600000 | E11: =C11-D11 -> 2000000 | F11: =F10+E11 -> 8500000
A12: Месяц 9 | B12: 6 | C12: 4050000 | D12: 2050000 | E12: =C12-D12 -> 2000000 | F12: =F11+E12 -> 10500000
A13: Месяц 10 | B13: 7 | C13: 4800000 | D13: 2300000 | E13: =C13-D13 -> 2500000 | F13: =F12+E13 -> 13000000
A14: Месяц 11 | B14: 7.5 | C14: 5400000 | D14: 2900000 | E14: =C14-D14 -> 2500000 | F14: =F13+E14 -> 15500000
A15: Месяц 12 | B15: 8 | C15: 6000000 | D15: 3500000 | E15: =C15-D15 -> 2500000 | F15: =F14+E15 -> 18000000
A16: Итого / Баланс | B16: =SUM(B4:B15) -> 59.5 | C16: =SUM(C4:C15) -> 38700000 | D16: =SUM(D4:D15) -> 20700000 | E16: =SUM(E4:E15) -> 18000000 | F16: =F15 -> 18000000
